[
  {
    "id": "savings-game-fire",
    "title": "【家計ハック】無理のないお得化をゲームにする！Side FIRE（月10万円セーブ）への第一歩",
    "date": "2026-06-29",
    "category": "お得化",
    "tags": [
      "節約",
      "家計管理",
      "ライフハック",
      "Side FIRE"
    ],
    "description": "サブスクの見直しや楽天市場のポイント上限、Kindleの読書ログを組み合わせ、無理のない節約・お得化をゲームのように楽しむロードマップを解説します。",
    "file": "../articles/2026-06-29-savings-game-fire.html",
    "thumbnail": "../articles/ogp/savings-game-fire.png"
  },
  {
    "id": "discount-gift-cards",
    "title": "Google Playギフトコードをお得に買う方法｜還元条件と注意点",
    "date": "2026-06-20",
    "category": "攻略",
    "tags": [
      "ギフトカード",
      "課金",
      "割引",
      "ポイント還元"
    ],
    "description": "Google Playギフトコードを楽天市場・コンビニ・決済還元で購入する前に、還元上限、対象外条件、期限、必要額を確認する方法を解説します。",
    "file": "../articles/2026-06-20-discount-gift-cards.html",
    "thumbnail": "../articles/ogp/discount-gift-cards.png"
  },
  {
    "id": "play-points-reflection-timing",
    "title": "Play Pointsはいつ反映される？遅い時の確認ポイントと待つ目安",
    "date": "2026-03-10",
    "category": "トラブル対処",
    "tags": [
      "Play Points",
      "反映タイミング",
      "保留",
      "確認方法"
    ],
    "description": "Play Pointsが反映されない時に、購入状態・履歴・アカウント・参加時期を順に確認する方法と問い合わせ前の準備を解説します。",
    "file": "../articles/2026-03-10-play-points-reflection-timing.html",
    "thumbnail": "../articles/ogp/2026-03-10-play-points-reflection-timing.png"
  },
  {
    "id": "multiple-accounts",
    "title": "Google Play Pointsは複数アカウントで合算できる？管理の注意点",
    "date": "2025-12-25",
    "category": "活用術",
    "tags": [
      "Play Points",
      "複数アカウント",
      "管理",
      "注意点"
    ],
    "description": "Google Play Pointsは複数のGoogleアカウント間で合算・移動できません。購入アカウントの確認方法、ポイント分散がランクへ与える影響を解説します。",
    "file": "../articles/2025-12-25-multiple-accounts.html",
    "thumbnail": "../articles/ogp/multiple-accounts.png"
  },
  {
    "id": "play-games",
    "title": "Google Play GamesとPlay Pointsの違い｜連携・ポイント獲得条件",
    "date": "2025-12-25",
    "category": "入門",
    "tags": [
      "Play Points",
      "Play Games",
      "違い",
      "関係"
    ],
    "description": "Google Play GamesとPlay Pointsの役割の違い、PC版を含む連携、遊ぶだけでポイントが貯まる例外条件をGoogle公式情報に沿って解説します。",
    "file": "../articles/2025-12-25-play-games.html",
    "thumbnail": "../articles/ogp/play-games.png"
  },
  {
    "id": "movies-books",
    "title": "Google Play Pointsは本・アプリ・サブスクでも貯まる？対象条件",
    "date": "2025-12-25",
    "category": "活用術",
    "tags": [
      "Play Points",
      "書籍",
      "アプリ",
      "定期購入"
    ],
    "description": "書籍、有料アプリ、アプリ内定期購入、Androidから契約したGoogle OneでPlay Pointsが貯まる条件と購入前後の確認方法を解説します。",
    "file": "../articles/2025-12-25-movies-books.html",
    "thumbnail": "../articles/ogp/movies-books.png"
  },
  {
    "id": "expiration",
    "title": "Google Play Pointsの有効期限｜失効日・確認方法・期限切れ対策",
    "date": "2025-12-25",
    "category": "入門",
    "tags": [
      "Play Points",
      "有効期限",
      "失効",
      "期限切れ"
    ],
    "description": "Google Play Pointsは最後の獲得・使用から1年で失効します。期限の確認方法、ランク進捗や交換後クレジットとの違い、失効対策を解説します。",
    "file": "../articles/2025-12-25-expiration.html",
    "thumbnail": "../articles/ogp/expiration.png"
  },
  {
    "id": "promo-code",
    "title": "プロモコード・割引時もGoogle Play Pointsは貯まる？確認方法",
    "date": "2025-12-25",
    "category": "活用術",
    "tags": [
      "Play Points",
      "プロモコード",
      "割引",
      "セール"
    ],
    "description": "プロモコードや割引利用時のPlay Pointsは特典条件で異なります。決済前の支払い額、併用条件、購入後のポイント履歴を確認する手順を解説します。",
    "file": "../articles/2025-12-25-promo-code.html",
    "thumbnail": "../articles/ogp/promo-code.png"
  },
  {
    "id": "check-balance",
    "title": "Google Play Pointsの残高・履歴・有効期限を確認する方法",
    "date": "2025-12-25",
    "category": "入門",
    "tags": [
      "Play Points",
      "残高",
      "履歴",
      "確認方法"
    ],
    "description": "Google Play Pointsの残高、ポイント履歴、有効期限、年間のレベル進捗を確認する手順と、計算機へ入力する数字の違いを解説します。",
    "file": "../articles/2025-12-25-check-balance.html",
    "thumbnail": "../articles/ogp/check-balance.png"
  },
  {
    "id": "refund",
    "title": "Google Play Pointsは返金でどうなる？残高・ランクへの影響",
    "date": "2025-12-25",
    "category": "トラブル対処",
    "tags": [
      "Play Points",
      "返金",
      "キャンセル",
      "減算"
    ],
    "description": "Google Playの返金後は獲得ポイントが残高とレベル進捗から減算されます。マイナス残高、ランク低下、定期購入キャンセルとの違いを解説します。",
    "file": "../articles/2025-12-25-refund.html",
    "thumbnail": "../articles/ogp/refund.png"
  },
  {
    "id": "gift-card",
    "title": "Google PlayギフトカードでPlay Pointsは貯まる？付与タイミング",
    "date": "2025-12-25",
    "category": "活用術",
    "tags": [
      "Play Points",
      "ギフトカード",
      "チャージ",
      "残高"
    ],
    "description": "Google Playギフトカードの購入、残高へのチャージ、対象コンテンツ購入を分け、Play Pointsが貯まるタイミングと対象外条件を解説します。",
    "file": "../articles/2025-12-25-gift-card.html",
    "thumbnail": "../articles/ogp/gift-card.png"
  },
  {
    "id": "family-sharing",
    "title": "Google Play Pointsは家族と共有できる？ファミリー利用の注意点",
    "date": "2025-12-25",
    "category": "活用術",
    "tags": [
      "Play Points",
      "ファミリー",
      "共有",
      "ファミリーライブラリ"
    ],
    "description": "Google Play Pointsは家族間でも合算・移動できません。ファミリーライブラリで共有できる範囲、購入アカウント、ギフトカードの注意点を解説します。",
    "file": "../articles/2025-12-25-family-sharing.html",
    "thumbnail": "../articles/ogp/family-sharing.png"
  },
  {
    "id": "subscription",
    "title": "Google One・アプリ内サブスクでPlay Pointsは貯まる？対象条件",
    "date": "2025-12-25",
    "category": "活用術",
    "tags": [
      "Play Points",
      "サブスク",
      "Google One",
      "アプリ内定期購入"
    ],
    "description": "Google Oneやアプリ内定期購入でPlay Pointsが貯まる条件を解説。支払い方法ではなくGoogle Play経由の請求かを確認する手順を紹介します。",
    "file": "../articles/2025-12-25-subscription.html",
    "thumbnail": "../articles/ogp/subscription.png"
  },
  {
    "id": "weekly-reward",
    "title": "Google Play Pointsのウィークリーリワード｜受け取り方・更新日・対象ランク",
    "date": "2025-12-25",
    "category": "入門",
    "tags": [
      "Play Points",
      "ウィークリーリワード",
      "無料",
      "毎週"
    ],
    "description": "通常のPlay PointsウィークリーリワードとPlay Pass週次特典の違い、対象ランク、受け取り方、日本での金曜・木曜更新を解説します。",
    "file": "../articles/2025-12-25-weekly-reward.html",
    "thumbnail": "../articles/ogp/weekly-reward.png"
  },
  {
    "id": "getting-started",
    "title": "Google Play Pointsの始め方｜登録方法と最初に確認すること",
    "date": "2025-12-25",
    "category": "入門",
    "tags": [
      "Play Points",
      "初心者",
      "登録",
      "始め方"
    ],
    "description": "Google Play Pointsとは？始め方・登録方法・最初にやるべきことを解説。ポイントの貯め方・使い方・ランク制度の基本まで。",
    "file": "../articles/2025-12-25-getting-started.html",
    "thumbnail": "../articles/ogp/getting-started.png"
  },
  {
    "id": "new-year-campaign",
    "title": "Google Play Pointsの年末年始キャンペーン｜開催確認と課金判断",
    "date": "2025-12-25",
    "category": "攻略",
    "tags": [
      "Play Points",
      "年末年始",
      "キャンペーン",
      "予測"
    ],
    "description": "Google Play Pointsの年末年始キャンペーンを過去日程だけで断定せず、自分のアカウントで開催期間・獲得率・有効化条件を確認する方法を解説します。",
    "file": "../articles/2025-12-25-new-year-campaign.html",
    "thumbnail": "../articles/ogp/new-year-campaign.png"
  },
  {
    "id": "diamond-vip",
    "title": "Google Play Pointsのダイヤモンド特典｜プラチナとの違いを検証",
    "date": "2025-12-25",
    "category": "検証",
    "tags": [
      "Play Points",
      "ダイヤモンド",
      "イベント",
      "体験価値"
    ],
    "description": "ダイヤモンドとプラチナの獲得率、週次リワード、プレミアムサポート、イベント特典を比較。ダイヤ固有の価値と共通特典を分けて解説します。",
    "file": "../articles/2025-12-25-diamond-vip.html",
    "thumbnail": "../articles/ogp/diamond-vip.png"
  },
  {
    "id": "campaign",
    "title": "Google Play Pointsのキャンペーンは待つべき？増量率の確認と課金判断",
    "date": "2025-12-25",
    "category": "攻略",
    "tags": [
      "Play Points",
      "キャンペーン",
      "増量",
      "倍率"
    ],
    "description": "Google Play Pointsの増量キャンペーンを待つべきか、対象アカウント、開始操作、最高獲得率、期限を確認し、通常時との必要額を比較する方法を解説します。",
    "file": "../articles/2025-12-25-campaign.html",
    "thumbnail": "../articles/ogp/campaign.png"
  },
  {
    "id": "best-use",
    "title": "Google Play Pointsの使い道を比較｜クーポン・アイテム・Playクレジットの選び方",
    "date": "2025-12-25",
    "category": "活用術",
    "tags": [
      "Play Points",
      "クーポン",
      "クレジット",
      "使い道"
    ],
    "description": "Google Play Pointsのクーポン、ゲーム内アイテム、Playクレジットを実用価値・最低購入額・期限で比較し、自分に合う交換先を選ぶ方法を解説します。",
    "file": "../articles/2025-12-25-best-use.html",
    "thumbnail": "../articles/ogp/best-use.png"
  },
  {
    "id": "diamond-worth-it",
    "title": "Google Play Pointsのダイヤモンドは得？必要ポイント・購入額・特典を比較",
    "date": "2025-12-25",
    "category": "検証",
    "tags": [
      "Play Points",
      "ダイヤモンド",
      "プラチナ",
      "シミュレーション"
    ],
    "description": "ダイヤモンドとプラチナの差を数字で検証。必要ポイント・維持費・どっちがコスパ良いかを解説。",
    "file": "../articles/2025-12-25-diamond-worth-it.html",
    "thumbnail": "../articles/ogp/diamond-worth-it.png"
  },
  {
    "id": "playpoints-rank-maintenance",
    "title": "Google Play Pointsのランク維持期間｜翌年末までの仕組みと年末の確認方法",
    "date": "2025-12-25",
    "category": "攻略",
    "tags": [
      "Play Points",
      "年末年始",
      "ランク維持"
    ],
    "description": "ランクは到達後、翌年末まで維持。暦年のレベル進捗、翌年の再判定、残高との違いを具体例で解説します。",
    "file": "../articles/2025-12-25-playpoints-rank-maintenance.html",
    "thumbnail": "../articles/ogp/playpoints-rank-maintenance.png"
  },
  {
    "id": "playpoints-not-reflected",
    "title": "Google Play Pointsが反映されない原因と確認手順",
    "date": "2025-12-25",
    "category": "トラブル対処",
    "tags": [
      "Play Points",
      "反映されない",
      "対処法"
    ],
    "description": "ポイント履歴・保留中・アカウント違いなど、よくある原因を公式手順でチェック。再起動やPlayストア更新の対処も解説。",
    "file": "../articles/2025-12-25-playpoints-not-reflected.html",
    "thumbnail": "../articles/ogp/playpoints-not-reflected.png"
  }
]
